tagreader/__init__.py
tagreader/__version__.py
tagreader/cache.py
tagreader/clients.py
tagreader/logger.py
tagreader/utils.py
tagreader/web_handlers.py
tagreader-6.2.0.dist-info/licenses/LICENSE
tagreader-6.2.0.dist-info/METADATA
tagreader-6.2.0.dist-info/WHEEL
tagreader-6.2.0.dist-info/RECORD
