Metadata-Version: 2.4
Name: tagreader
Version: 6.2.0
Summary: Tagreader is a Python package for reading trend data from the OSIsoft PI and Aspen Infoplus.21 IMS systems.
License-Expression: MIT
License-File: LICENSE
Keywords: Aspen InfoPlus.21,OSIsoft PI
Author: Einar S. Idsø
Author-email: eiids@equinor.com
Requires-Python: >=3.9.2,<4.0.0
Classifier: Development Status :: 5 - Production/Stable
Classifier: Intended Audience :: Developers
Classifier: Intended Audience :: Science/Research
Classifier: License :: OSI Approved :: MIT License
Classifier: Natural Language :: English
Classifier: Operating System :: MacOS
Classifier: Operating System :: Microsoft :: Windows
Classifier: Operating System :: POSIX :: Linux
Classifier: Programming Language :: Python :: 3.9
Classifier: Programming Language :: Python :: 3.10
Classifier: Programming Language :: Python :: 3.11
Classifier: Programming Language :: Python :: 3.12
Classifier: Topic :: Scientific/Engineering :: Interface Engine/Protocol Translator
Classifier: Topic :: Software Development :: Libraries :: Python Modules
Classifier: Topic :: Utilities
Requires-Dist: certifi (>=2024.12.14,<2026.0.0)
Requires-Dist: diskcache (>=5.6.1)
Requires-Dist: msal-bearer (>=1.3.3)
Requires-Dist: pandas (>=1)
Requires-Dist: platformdirs (>=4.3.7)
Requires-Dist: pycryptodome (>=3.20.0)
Requires-Dist: requests (>=2.32.5)
Requires-Dist: requests-kerberos (>=0)
Requires-Dist: requests-ntlm (>=1.1,<=2.0)
Requires-Dist: urllib3 (>=2.5.0)
Project-URL: Homepage, https://github.com/equinor/tagreader-python
Project-URL: Repository, https://github.com/equinor/tagreader-python
